census_api/__init__.py
census_api/census_query.py
census_api/utils.py
census_api-0.0.2.dist-info/METADATA
census_api-0.0.2.dist-info/WHEEL
census_api-0.0.2.dist-info/top_level.txt
census_api-0.0.2.dist-info/RECORD
