Metadata-Version: 2.1
Name: census-api
Version: 0.0.2
Summary: Python wrapper to query the US Census API
Home-page: https://github.com/chrispyles/census_api
Author: Chris Pyles
Author-email: cpyles@berkeley.edu
License: BSD-3-Clause
Platform: UNKNOWN
Classifier: Programming Language :: Python :: 3
Classifier: License :: OSI Approved :: BSD License
Classifier: Operating System :: OS Independent
